LICENSE
MANIFEST.in
README.rst
setup.py
django_formalizr.egg-info/PKG-INFO
django_formalizr.egg-info/SOURCES.txt
django_formalizr.egg-info/dependency_links.txt
django_formalizr.egg-info/not-zip-safe
django_formalizr.egg-info/requires.txt
django_formalizr.egg-info/top_level.txt
formalizr/__init__.py
formalizr/decorators.py
formalizr/models.py
formalizr/views.py