Metadata-Version: 1.0
Name: django-formalizr
Version: 1
Summary: Django AJAX Class Based Views
Home-page: https://github.com/krasnoperov/django-formalizr
Author: Aleksei Krasnoperov
Author-email: aleksei@krasnoperov.me
License: BSD License
Platform: UNKNOWN
Classifier: Environment :: Web Environment
Classifier: Framework :: Django
Classifier: Intended Audience :: Developers
Classifier: License :: OSI Approved :: BSD License
Classifier: Operating System :: OS Independent
Classifier: Programming Language :: Python
Classifier: Programming Language :: Python :: 2.7
Classifier: Topic :: Software Development :: Libraries :: Python Modules
